{
  "allQuestionsCount": [
    { "difficulty": "All", "count": 3045 },
    { "difficulty": "Easy", "count": 771 },
    { "difficulty": "Medium", "count": 1599 },
    { "difficulty": "Hard", "count": 675 }
  ],
  "matchedUser": {
    "username": "lldan",
    "socialAccounts": null,
    "githubUrl": "https://github.com/lld4n",
    "contributions": { "points": 1803, "questionCount": 0, "testcaseCount": 0 },
    "profile": {
      "realName": "lldan",
      "websites": ["https://lldan.ru"],
      "countryName": "Russia",
      "skillTags": ["typescript"],
      "company": null,
      "school": null,
      "starRating": 3,
      "aboutMe": "Frontend Developer",
      "userAvatar": "https://assets.leetcode.com/users/avatars/avatar_1681509769.png",
      "reputation": 3,
      "ranking": 86056
    },
    "submissionCalendar": "{\"1704067200\": 1, \"1704153600\": 1, \"1704240000\": 1, \"1704326400\": 4, \"1704412800\": 1, \"1704499200\": 1, \"1704585600\": 2, \"1704672000\": 1, \"1704758400\": 2, \"1704844800\": 5, \"1704931200\": 1, \"1705017600\": 2, \"1705104000\": 1, \"1705190400\": 1, \"1705276800\": 1, \"1705363200\": 7, \"1705449600\": 1, \"1705536000\": 1, \"1705622400\": 1, \"1705708800\": 3, \"1705795200\": 3, \"1705881600\": 1, \"1705968000\": 4, \"1706054400\": 8, \"1706140800\": 1, \"1706227200\": 6, \"1706313600\": 1, \"1706400000\": 4, \"1706486400\": 3, \"1706572800\": 2, \"1706659200\": 2, \"1706745600\": 1, \"1706832000\": 1, \"1706918400\": 1, \"1707004800\": 6, \"1707091200\": 22, \"1707177600\": 21, \"1707264000\": 50, \"1707350400\": 16, \"1707436800\": 21, \"1707523200\": 37, \"1707609600\": 25, \"1707696000\": 30, \"1707782400\": 24, \"1707868800\": 2, \"1707955200\": 3, \"1708041600\": 3, \"1708128000\": 5, \"1708214400\": 1, \"1708300800\": 1, \"1708387200\": 1, \"1708473600\": 10, \"1708560000\": 16, \"1708646400\": 41, \"1708732800\": 7, \"1687651200\": 25, \"1687737600\": 22, \"1697328000\": 5, \"1697414400\": 6, \"1697673600\": 11, \"1697932800\": 21, \"1698105600\": 2, \"1698278400\": 19, \"1698364800\": 12, \"1698451200\": 25, \"1698537600\": 6, \"1698624000\": 13, \"1698710400\": 10, \"1698796800\": 12, \"1698883200\": 2, \"1698969600\": 7, \"1699056000\": 3, \"1699142400\": 6, \"1699228800\": 40, \"1699315200\": 60, \"1699401600\": 6, \"1699488000\": 32, \"1699574400\": 1, \"1699660800\": 2, \"1699747200\": 2, \"1699833600\": 1, \"1699920000\": 1, \"1700006400\": 1, \"1700092800\": 1, \"1700179200\": 2, \"1700265600\": 2, \"1700352000\": 2, \"1700438400\": 1, \"1700524800\": 2, \"1700611200\": 4, \"1700697600\": 1, \"1700784000\": 1, \"1700870400\": 4, \"1700956800\": 4, \"1701043200\": 1, \"1701129600\": 32, \"1701216000\": 1, \"1701302400\": 7, \"1701388800\": 15, \"1701475200\": 1, \"1701561600\": 2, \"1701648000\": 1, \"1701734400\": 1, \"1701820800\": 1, \"1701907200\": 2, \"1701993600\": 1, \"1702080000\": 1, \"1702166400\": 1, \"1702252800\": 1, \"1702339200\": 1, \"1702425600\": 1, \"1702512000\": 2, \"1702598400\": 1, \"1702684800\": 1, \"1702771200\": 2, \"1702857600\": 1, \"1702944000\": 1, \"1703030400\": 1, \"1703116800\": 1, \"1703203200\": 1, \"1703289600\": 1, \"1703376000\": 1, \"1703462400\": 13, \"1703548800\": 3, \"1703635200\": 1, \"1703721600\": 3, \"1703808000\": 1, \"1703894400\": 1, \"1703980800\": 1}",
    "submitStats": {
      "acSubmissionNum": [
        { "difficulty": "All", "count": 507, "submissions": 585 },
        { "difficulty": "Easy", "count": 365, "submissions": 421 },
        { "difficulty": "Medium", "count": 117, "submissions": 136 },
        { "difficulty": "Hard", "count": 25, "submissions": 28 }
      ],
      "totalSubmissionNum": [
        { "difficulty": "All", "count": 513, "submissions": 901 },
        { "difficulty": "Easy", "count": 365, "submissions": 542 },
        { "difficulty": "Medium", "count": 122, "submissions": 283 },
        { "difficulty": "Hard", "count": 26, "submissions": 76 }
      ]
    },
    "badges": [
      {
        "id": "3369461",
        "displayName": "50 Days Badge 2024",
        "icon": "https://assets.leetcode.com/static_assets/marketing/2024-50-lg.png",
        "creationDate": "2024-02-19"
      },
      {
        "id": "2881726",
        "displayName": "50 Days Badge 2023",
        "icon": "https://assets.leetcode.com/static_assets/marketing/lg50.png",
        "creationDate": "2023-12-16"
      },
      {
        "id": "3252582",
        "displayName": "Jan LeetCoding Challenge",
        "icon": "/static/images/badges/dcc-2024-1.png",
        "creationDate": "2024-01-31"
      },
      {
        "id": "3151325",
        "displayName": "Dec LeetCoding Challenge",
        "icon": "/static/images/badges/dcc-2023-12.png",
        "creationDate": "2023-12-31"
      },
      {
        "id": "2692923",
        "displayName": "Nov LeetCoding Challenge",
        "icon": "/static/images/badges/dcc-2023-11.png",
        "creationDate": "2023-11-30"
      }
    ],
    "upcomingBadges": [
      {
        "name": "Feb LeetCoding Challenge",
        "icon": "/static/images/badges/dcc-2024-2.png"
      }
    ],
    "activeBadge": { "id": "3369461" }
  },
  "recentSubmissionList": [
    {
      "title": "Check if Word Equals Summation of Two Words",
      "titleSlug": "check-if-word-equals-summation-of-two-words",
      "timestamp": "1708774474",
      "statusDisplay": "Accepted",
      "lang": "typescript"
    },
    {
      "title": "Check if Word Equals Summation of Two Words",
      "titleSlug": "check-if-word-equals-summation-of-two-words",
      "timestamp": "1708774356",
      "statusDisplay": "Wrong Answer",
      "lang": "typescript"
    },
    {
      "title": "Find All People With Secret",
      "titleSlug": "find-all-people-with-secret",
      "timestamp": "1708774101",
      "statusDisplay": "Accepted",
      "lang": "typescript"
    },
    {
      "title": "Find All People With Secret",
      "titleSlug": "find-all-people-with-secret",
      "timestamp": "1708770937",
      "statusDisplay": "Time Limit Exceeded",
      "lang": "typescript"
    },
    {
      "title": "Find All People With Secret",
      "titleSlug": "find-all-people-with-secret",
      "timestamp": "1708770752",
      "statusDisplay": "Time Limit Exceeded",
      "lang": "typescript"
    },
    {
      "title": "Find All People With Secret",
      "titleSlug": "find-all-people-with-secret",
      "timestamp": "1708769659",
      "statusDisplay": "Wrong Answer",
      "lang": "typescript"
    },
    {
      "title": "Find All People With Secret",
      "titleSlug": "find-all-people-with-secret",
      "timestamp": "1708769120",
      "statusDisplay": "Wrong Answer",
      "lang": "typescript"
    },
    {
      "title": "Determine Whether Matrix Can Be Obtained By Rotation",
      "titleSlug": "determine-whether-matrix-can-be-obtained-by-rotation",
      "timestamp": "1708717960",
      "statusDisplay": "Accepted",
      "lang": "typescript"
    },
    {
      "title": "Check if All the Integers in a Range Are Covered",
      "titleSlug": "check-if-all-the-integers-in-a-range-are-covered",
      "timestamp": "1708717702",
      "statusDisplay": "Accepted",
      "lang": "typescript"
    },
    {
      "title": "Longest Unequal Adjacent Groups Subsequence I",
      "titleSlug": "longest-unequal-adjacent-groups-subsequence-i",
      "timestamp": "1708717257",
      "statusDisplay": "Accepted",
      "lang": "typescript"
    },
    {
      "title": "Longest Unequal Adjacent Groups Subsequence I",
      "titleSlug": "longest-unequal-adjacent-groups-subsequence-i",
      "timestamp": "1708717024",
      "statusDisplay": "Wrong Answer",
      "lang": "typescript"
    },
    {
      "title": "Longest Unequal Adjacent Groups Subsequence I",
      "titleSlug": "longest-unequal-adjacent-groups-subsequence-i",
      "timestamp": "1708716836",
      "statusDisplay": "Wrong Answer",
      "lang": "typescript"
    },
    {
      "title": "Longest Unequal Adjacent Groups Subsequence I",
      "titleSlug": "longest-unequal-adjacent-groups-subsequence-i",
      "timestamp": "1708716317",
      "statusDisplay": "Wrong Answer",
      "lang": "typescript"
    },
    {
      "title": "Remove One Element to Make the Array Strictly Increasing",
      "titleSlug": "remove-one-element-to-make-the-array-strictly-increasing",
      "timestamp": "1708715361",
      "statusDisplay": "Accepted",
      "lang": "typescript"
    },
    {
      "title": "Remove One Element to Make the Array Strictly Increasing",
      "titleSlug": "remove-one-element-to-make-the-array-strictly-increasing",
      "timestamp": "1708715100",
      "statusDisplay": "Wrong Answer",
      "lang": "typescript"
    },
    {
      "title": "Count Square Sum Triples",
      "titleSlug": "count-square-sum-triples",
      "timestamp": "1708714557",
      "statusDisplay": "Accepted",
      "lang": "typescript"
    },
    {
      "title": "Maximum Number of Words You Can Type",
      "titleSlug": "maximum-number-of-words-you-can-type",
      "timestamp": "1708714447",
      "statusDisplay": "Accepted",
      "lang": "typescript"
    },
    {
      "title": "Check if All Characters Have Equal Number of Occurrences",
      "titleSlug": "check-if-all-characters-have-equal-number-of-occurrences",
      "timestamp": "1708714198",
      "statusDisplay": "Accepted",
      "lang": "typescript"
    },
    {
      "title": "Sum of Digits of String After Convert",
      "titleSlug": "sum-of-digits-of-string-after-convert",
      "timestamp": "1708713957",
      "statusDisplay": "Accepted",
      "lang": "typescript"
    },
    {
      "title": "Three Divisors",
      "titleSlug": "three-divisors",
      "timestamp": "1708704755",
      "statusDisplay": "Accepted",
      "lang": "typescript"
    }
  ]
}
